[
  {
    "outputFile": "wwwroot/css/site.css",
    "inputFile": "wwwroot/raw/css/site.less"
  },
  {
    "outputFile": "wwwroot/js/site.js",
    "inputFile": "wwwroot/raw/js/site.js"
  },
  {
    "outputFile": "wwwroot/js/_layout_section.js",
    "inputFile": "wwwroot/raw/js/_layout_section.js"
  },
  {
    "outputFile": "wwwroot/js/_table.js",
    "inputFile": "wwwroot/raw/js/_table.js"
  },
  {
    "outputFile": "wwwroot/css/sharedheader.css",
    "inputFile": "wwwroot/raw/shared/sharedheader.less"
  },
  {
    "outputFile": "wwwroot/css/sharedfooter.css",
    "inputFile": "wwwroot/raw/shared/sharedfooter.less"
  },
  {
    "outputFile": "wwwroot/js/sharedheader.js",
    "inputFile": "wwwroot/raw/shared/sharedheader.js"
  },
  {
    "outputFile": "wwwroot/css/board.css",
    "inputFile": "wwwroot/raw/css/board.less"
  },
  {
    "outputFile": "wwwroot/css/index.css",
    "inputFile": "wwwroot/raw/css/index.less"
  },
  {
    "outputFile": "wwwroot/js/index.js",
    "inputFile": "wwwroot/raw/js/index.js"
  },
  {
    "outputFile": "wwwroot/css/newuser.css",
    "inputFile": "wwwroot/raw/css/newuser.less"
  },
  {
    "outputFile": "wwwroot/js/newuser.js",
    "inputFile": "wwwroot/raw/js/newuser.js"
  },
  {
    "outputFile": "wwwroot/css/create.css",
    "inputFile": "wwwroot/raw/css/create.less"
  },
  {
    "outputFile": "wwwroot/js/create.js",
    "inputFile": "wwwroot/raw/js/create.js"
  },
  {
    "outputFile": "wwwroot/css/detail.css",
    "inputFile": "wwwroot/raw/css/detail.less"
  },
  {
    "outputFile": "wwwroot/css/groups/index.css",
    "inputFile": "wwwroot/raw/css/groups/index.less"
  }
]